scanner.py
supply_chain_scanner-1.0.0.dist-info/licenses/LICENSE
tests/__init__.py
tests/test_scanner.py
supply_chain_scanner-1.0.0.dist-info/METADATA
supply_chain_scanner-1.0.0.dist-info/WHEEL
supply_chain_scanner-1.0.0.dist-info/entry_points.txt
supply_chain_scanner-1.0.0.dist-info/top_level.txt
supply_chain_scanner-1.0.0.dist-info/RECORD
