Metadata-Version: 2.4
Name: supply-chain-scanner
Version: 1.0.0
Summary: A comprehensive security tool to detect compromised NPM packages in Git repositories
Home-page: https://github.com/security-community/supply-chain-scanner
Author: Security Community
Author-email: Security Community <security@community.org>
Maintainer-email: Security Community <security@community.org>
License: MIT
Project-URL: Homepage, https://github.com/security-community/supply-chain-scanner
Project-URL: Documentation, https://github.com/security-community/supply-chain-scanner/wiki
Project-URL: Repository, https://github.com/security-community/supply-chain-scanner.git
Project-URL: Bug Reports, https://github.com/security-community/supply-chain-scanner/issues
Project-URL: Changelog, https://github.com/security-community/supply-chain-scanner/blob/main/CHANGELOG.md
Keywords: security,supply-chain,npm,vulnerability,scanner,github,gitlab
Classifier: Development Status :: 5 - Production/Stable
Classifier: Intended Audience :: Developers
Classifier: Intended Audience :: System Administrators
Classifier: Topic :: Security
Classifier: Topic :: Software Development :: Quality Assurance
Classifier: Topic :: System :: Systems Administration
Classifier: License :: OSI Approved :: MIT License
Classifier: Programming Language :: Python :: 3
Classifier: Programming Language :: Python :: 3.8
Classifier: Programming Language :: Python :: 3.9
Classifier: Programming Language :: Python :: 3.10
Classifier: Programming Language :: Python :: 3.11
Classifier: Programming Language :: Python :: 3.12
Classifier: Operating System :: OS Independent
Requires-Python: >=3.8
License-File: LICENSE
Requires-Dist: requests>=2.28.0
Requires-Dist: PyYAML>=6.0
Requires-Dist: urllib3>=1.26.0
Provides-Extra: dev
Requires-Dist: pytest>=7.0.0; extra == "dev"
Requires-Dist: pytest-cov>=4.0.0; extra == "dev"
Requires-Dist: pytest-mock>=3.10.0; extra == "dev"
Requires-Dist: black>=22.0.0; extra == "dev"
Requires-Dist: flake8>=5.0.0; extra == "dev"
Requires-Dist: mypy>=0.991; extra == "dev"
Requires-Dist: types-requests; extra == "dev"
Requires-Dist: types-PyYAML; extra == "dev"
Requires-Dist: bandit>=1.7.0; extra == "dev"
Requires-Dist: isort>=5.12.0; extra == "dev"
Requires-Dist: pre-commit>=2.20.0; extra == "dev"
Requires-Dist: build>=0.8.0; extra == "dev"
Requires-Dist: twine>=4.0.0; extra == "dev"
Dynamic: author
Dynamic: home-page
Dynamic: license-file
Dynamic: requires-python
